facilities/__init__.py
facilities/facilities_scrape.py
facilities/facility_en.py
facilities/katedry-scrape.py
facilities/rozvrh-filtr.py
facilities/rozvrh-scrape.py
facilities/systemdata_create.py
facilities/__pycache__/facilities_scrape.cpython-311.pyc
facilities/__pycache__/facility_en.cpython-311.pyc
facilities/__pycache__/json.cpython-311.pyc
facilities/__pycache__/scrape_basic.cpython-311.pyc
facilities/__pycache__/systemdata_create.cpython-311.pyc
facilities-0.1.2.dist-info/LICENSE
facilities-0.1.2.dist-info/METADATA
facilities-0.1.2.dist-info/WHEEL
facilities-0.1.2.dist-info/top_level.txt
facilities-0.1.2.dist-info/RECORD
