Metadata-Version: 2.1
Name: facilities
Version: 0.1.2
Summary: Package for facilities scrape
Home-page: https://github.com/Vitek233/FACILITIES
Author: RS
Author-email: 
Classifier: Programming Language :: Python :: 3
Classifier: License :: OSI Approved :: MIT License
Classifier: Operating System :: OS Independent
Requires-Python: >=3.6
License-File: LICENSE
